src/railway_controller.v
module railway_controller (
    input clk,
    input reset,
    input train_arrival,
    input train_departure,

    output reg gate,
    output reg warning,
    output reg road_signal,

    output [1:0] state_out
);

    
    parameter IDLE          = 2'b00;
    parameter GATE_CLOSING  = 2'b01;
    parameter TRAIN_PASSING = 2'b10;
    parameter GATE_OPENING  = 2'b11;

    reg [1:0] current_state;
    reg [1:0] next_state;

    
    assign state_out = current_state;

    
    always @(posedge clk or posedge reset) begin
        if (reset)
            current_state <= IDLE;
        else
            current_state <= next_state;
    end

    
    always @(*) begin
        case (current_state)

            IDLE:
                if (train_arrival)
                    next_state = GATE_CLOSING;
                else
                    next_state = IDLE;

            GATE_CLOSING:
                next_state = TRAIN_PASSING;

            TRAIN_PASSING:
                if (train_departure)
                    next_state = GATE_OPENING;
                else
                    next_state = TRAIN_PASSING;

            GATE_OPENING:
                next_state = IDLE;

            default:
                next_state = IDLE;

        endcase
    end

    
    always @(*) begin

        gate        = 1'b0;
        warning     = 1'b0;
        road_signal = 1'b0;

        case(current_state)

            IDLE: begin
                gate        = 1'b0;   // Open
                warning     = 1'b0;
                road_signal = 1'b0;   // Green
            end

            GATE_CLOSING: begin
                gate        = 1'b1;   // Closed
                warning     = 1'b1;
                road_signal = 1'b1;   // Red
            end

            TRAIN_PASSING: begin
                gate        = 1'b1;
                warning     = 1'b1;
                road_signal = 1'b1;
            end

            GATE_OPENING: begin
                gate        = 1'b0;   // Open
                warning     = 1'b0;
                road_signal = 1'b0;   // Green
            end

            default: begin
                gate        = 1'b0;
                warning     = 1'b0;
                road_signal = 1'b0;
            end

        endcase

    end

endmodule

tb/tb_railway_controller.v
`timescale 1ns/1ps

module tb_railway_controller;

    
    reg clk;
    reg reset;
    reg train_arrival;
    reg train_departure;

    
    wire gate;
    wire warning;
    wire road_signal;
    wire [1:0] state_out;

    
    railway_controller uut (
        .clk(clk),
        .reset(reset),
        .train_arrival(train_arrival),
        .train_departure(train_departure),
        .gate(gate),
        .warning(warning),
        .road_signal(road_signal),
        .state_out(state_out)
    );

    
    initial begin
        clk = 0;
        forever #5 clk = ~clk;
    end

    
    initial begin
        $dumpfile("railway.vcd");
        $dumpvars(0, tb_railway_controller);
    end

    
    initial begin

        reset = 1;
        train_arrival = 0;
        train_departure = 0;

        #20;
        reset = 0;

        
        #20;
        train_arrival = 1;

        #10;
        train_arrival = 0;

        #60;
        train_departure = 1;

        #10;
        train_departure = 0;

        #40;

        
        train_arrival = 1;

        #10;
        train_arrival = 0;

        #40;
        train_departure = 1;

        #10;
        train_departure = 0;

        #40;

        
        train_arrival = 1;

        #10;
        train_arrival = 0;

        #20;
        reset = 1;

        #10;
        reset = 0;

        #40;

        $finish;

    end

    
    initial begin
        $monitor("Time=%0t Reset=%b Arr=%b Dep=%b State=%b Gate=%b Warn=%b Road=%b",
                  $time,
                  reset,
                  train_arrival,
                  train_departure,
                  state_out,
                  gate,
                  warning,
                  road_signal);
    end

endmodule

waveform/railway.vcd
$date
	Wed Jul 22 20:51:55 2026
$end
$version
	Icarus Verilog
$end
$timescale
	1ps
$end
$scope module tb_railway_controller $end
$var wire 1 ! warning $end
$var wire 2 " state_out [1:0] $end
$var wire 1 # road_signal $end
$var wire 1 $ gate $end
$var reg 1 % clk $end
$var reg 1 & reset $end
$var reg 1 ' train_arrival $end
$var reg 1 ( train_departure $end
$scope module uut $end
$var wire 1 % clk $end
$var wire 1 & reset $end
$var wire 2 ) state_out [1:0] $end
$var wire 1 ' train_arrival $end
$var wire 1 ( train_departure $end
$var parameter 2 * GATE_CLOSING $end
$var parameter 2 + GATE_OPENING $end
$var parameter 2 , IDLE $end
$var parameter 2 - TRAIN_PASSING $end
$var reg 2 . current_state [1:0] $end
$var reg 1 $ gate $end
$var reg 2 / next_state [1:0] $end
$var reg 1 # road_signal $end
$var reg 1 ! warning $end
$upscope $end
$upscope $end
$enddefinitions $end
$comment Show the parameter values. $end
$dumpall
b10 -
b0 ,
b11 +
b1 *
$end
#0
$dumpvars
b0 /
b0 .
b0 )
0(
0'
1&
0%
0$
0#
b0 "
0!
$end
#5000
1%
#10000
0%
#15000
1%
#20000
0%
0&
#25000
1%
#30000
0%
#35000
1%
#40000
b1 /
0%
1'
#45000
1#
1!
1$
b10 /
b1 "
b1 )
b1 .
1%
#50000
0%
0'
#55000
1#
1!
1$
b10 "
b10 )
b10 .
1%
#60000
0%
#65000
1%
#70000
0%
#75000
1%
#80000
0%
#85000
1%
#90000
0%
#95000
1%
#100000
0%
#105000
1%
#110000
b11 /
0%
1(
#115000
0#
0!
0$
b0 /
b11 "
b11 )
b11 .
1%
#120000
0%
0(
#125000
b0 "
b0 )
b0 .
1%
#130000
0%
#135000
1%
#140000
0%
#145000
1%
#150000
0%
#155000
1%
#160000
b1 /
0%
1'
#165000
1#
1!
1$
b10 /
b1 "
b1 )
b1 .
1%
#170000
0%
0'
#175000
1#
1!
1$
b10 "
b10 )
b10 .
1%
#180000
0%
#185000
1%
#190000
0%
#195000
1%
#200000
0%
#205000
1%
#210000
b11 /
0%
1(
#215000
0#
0!
0$
b0 /
b11 "
b11 )
b11 .
1%
#220000
0%
0(
#225000
b0 "
b0 )
b0 .
1%
#230000
0%
#235000
1%
#240000
0%
#245000
1%
#250000
0%
#255000
1%
#260000
b1 /
0%
1'
#265000
1#
1!
1$
b10 /
b1 "
b1 )
b1 .
1%
#270000
0%
0'
#275000
1#
1!
1$
b10 "
b10 )
b10 .
1%
#280000
0%
#285000
1%
#290000
0#
0!
0$
b0 /
b0 "
b0 )
b0 .
0%
1&
#295000
1%
#300000
0%
0&
